.DS_Store
texmd/__init__.py
texmd/bib.py
texmd/md.py
texmd/tex.py
texmd/texmd.py
texmd-0.1.2.dist-info/LICENSE
texmd-0.1.2.dist-info/METADATA
texmd-0.1.2.dist-info/WHEEL
texmd-0.1.2.dist-info/top_level.txt
texmd-0.1.2.dist-info/RECORD
